catfact/__init__.py
catfact/_databackend.py
catfact/add_rm.py
catfact/misc.py
catfact/reorder.py
catfact/values.py
catfact/data/__init__.py
catfact/data/gdp.csv
catfact/data/ratings.csv
catfact/data/ratings_messy.csv
catfact/data/starwars.csv
catfact/pandas/__init__.py
catfact/pandas/_namespace.py
catfact/pandas/data.py
catfact/polars/__init__.py
catfact/polars/_namespace.py
catfact/polars/data.py
catfact/tests/test_fct_order.py
catfact/tests/test_fct_values.py
catfact/tests/test_misc.py
catfact-0.1.0.dist-info/licenses/LICENSE
catfact-0.1.0.dist-info/METADATA
catfact-0.1.0.dist-info/WHEEL
catfact-0.1.0.dist-info/top_level.txt
catfact-0.1.0.dist-info/RECORD
