Metadata-Version: 2.4
Name: catfact
Version: 0.1.0
Summary: Add your description here
License: MIT License
Keywords: factors,categoricals
Requires-Python: >=3.10
License-File: LICENSE
Requires-Dist: databackend>=0.0.3
Requires-Dist: ddispatch>=0.0.1
Requires-Dist: polars
Dynamic: license-file
